napari_feature_classifier/__init__.py
napari_feature_classifier/annotator_init_widget.py
napari_feature_classifier/annotator_widget.py
napari_feature_classifier/classifier.py
napari_feature_classifier/classifier_widget.py
napari_feature_classifier/dev_main.py
napari_feature_classifier/feature_loader_widget.py
napari_feature_classifier/napari.yaml
napari_feature_classifier/utils.py
napari_feature_classifier/_tests/__init__.py
napari_feature_classifier/_tests/test_annotator_widgets.py
napari_feature_classifier/_tests/test_classifier.py
napari_feature_classifier/_tests/test_classifier_widget.py
napari_feature_classifier/_tests/test_feature_loading.py
napari_feature_classifier-0.3.2.dist-info/licenses/LICENSE
napari_feature_classifier-0.3.2.dist-info/METADATA
napari_feature_classifier-0.3.2.dist-info/WHEEL
napari_feature_classifier-0.3.2.dist-info/entry_points.txt
napari_feature_classifier-0.3.2.dist-info/top_level.txt
napari_feature_classifier-0.3.2.dist-info/RECORD
