Metadata-Version: 2.4
Name: napari-feature-classifier
Version: 0.3.2
Summary: An interactive classifier plugin to use with label images and feature measurements
Home-page: https://github.com/fractal-napari-plugins-collection/napari-feature-classifier
Author: Joel Luethi and Max Hess
Author-email: joel.luethi@uzh.ch
License: BSD-3-Clause
Project-URL: Bug Tracker, https://github.com/fractal-napari-plugins-collection/napari-feature-classifier/issues
Project-URL: Documentation, https://github.com/fractal-napari-plugins-collection/napari-feature-classifier#napari-feature-classifier
Project-URL: Source Code, https://github.com/fractal-napari-plugins-collection/napari-feature-classifier
Project-URL: User Support, https://github.com/fractal-napari-plugins-collection/napari-feature-classifier/issues
Classifier: Development Status :: 3 - Alpha
Classifier: Intended Audience :: Developers
Classifier: Framework :: napari
Classifier: Topic :: Software Development :: Testing
Classifier: Programming Language :: Python
Classifier: Programming Language :: Python :: 3
Classifier: Programming Language :: Python :: 3.9
Classifier: Programming Language :: Python :: 3.10
Classifier: Operating System :: OS Independent
Classifier: License :: OSI Approved :: BSD License
Requires-Python: >=3.9
License-File: LICENSE
Requires-Dist: numpy
Requires-Dist: napari
Requires-Dist: matplotlib
Requires-Dist: magicgui
Requires-Dist: pandas>=2.2.0
Requires-Dist: scikit-learn>=1.2.2
Requires-Dist: pandera
Requires-Dist: xxhash
Requires-Dist: hypothesis
Dynamic: license-file
